Metadata-Version: 2.1
Name: nkeys
Version: 0.2.1
Summary: A public-key signature system based on Ed25519 for the NATS ecosystem.
Author-email: Waldemar Quevedo <wally@nats.io>
License: Apache 2 License
Project-URL: Homepage, https://github.com/nats-io/nkeys.py
Project-URL: Bug Tracker, https://github.com/nats-io/nkeys.py/issues
Classifier: License :: OSI Approved :: Apache Software License
Classifier: Intended Audience :: Developers
Classifier: Programming Language :: Python
Classifier: Programming Language :: Python :: 3
Classifier: Programming Language :: Python :: 3.6
Classifier: Programming Language :: Python :: 3.7
Classifier: Programming Language :: Python :: 3.8
Classifier: Programming Language :: Python :: 3.9
Classifier: Programming Language :: Python :: 3.10
Classifier: Programming Language :: Python :: 3.11
Classifier: Programming Language :: Python :: 3.12
Classifier: Programming Language :: Python :: Implementation :: CPython
Requires-Python: >=3.6
License-File: LICENSE
Requires-Dist: pynacl
